MikeyBots/__init__.py
MikeyBots-4.2.1.dist-info/METADATA
MikeyBots-4.2.1.dist-info/WHEEL
MikeyBots-4.2.1.dist-info/top_level.txt
MikeyBots-4.2.1.dist-info/RECORD
