Metadata-Version: 2.1
Name: MikeyBots
Version: 4.2.1
Summary: Async Tool For MikeyBots
Home-page: https://pirxcypingerfinal.pirxcyfinal.repl.co/
Author: MikeyBots
License: UNKNOWN
Platform: UNKNOWN
Classifier: Programming Language :: Python :: 3
Classifier: License :: OSI Approved :: MIT License
Classifier: Operating System :: OS Independent
Requires-Dist: aiohttp
